{"type": "FeatureCollection", "features": [{"type": "Feature", "geometry": {"type": "Point", "coordinates": [-72.81284632825468, -47.0518018424338]}, "properties": {"FID_Fluvio": 401, "REGION": "11", "COD_BNA": "11530000-8", "NOMBRE": "RIO BAKER EN DESAGUE LAGO BERTRAND", "ESTADO": "Vigente", "ESTE_84": 666116, "NORTE_84": 4786758, "COD_CUEN": "115", "COD_SUBC": "1153", "COD_SSUBC": "11533", "NOM_SSUBC": "Rio Baker Entre Desague Lago Bertrand y Rio Chacabuco", "NOM_CUEN": "Rio Baker", "NOM_SUBC": "R. Baker entre Desague L. J. M. Carrera y R. de La Colonia", "CINE_REG": "11", "COD_REG": 11, "NOM_REG": "Ays\u00e9n del General Carlos Ib\u00e1\u00f1ez del Campo", "CINE_PROV": "114", "COD_PROV": 114, "NOM_PROV": "General Carrera", "CINE_COM": "11401", "COD_COM": 11401, "NOM_COM": "Chile Chico", "LAT": -47.0518018424, "LONG": -72.8128463283, "FID_comuna": 19332, "CUT_REG": "11", "CUT_PROV": "114", "CUT_COM": "11401", "REGION_1": "Ays\u00e9n del General Carlos Ib\u00e1\u00f1ez del Campo", "PROVINCIA": "General Carrera", "COMUNA": "Chile Chico", "COD_CUEN_1": "115", "COD_SUBC_1": "1153", "COD_SSUB_1": "11533", "NOM_SSUB_1": "Rio Baker Entre Desague Lago Bertrand y Rio Chacabuco", "Hectareas": 4875.00073808}}, {"type": "Feature", "geometry": {"type": "Point", "coordinates": [-72.80320343686944, -46.846451449856886]}, "properties": {"FID_Fluvio": 400, "REGION": "11", "COD_BNA": "11517002-3", "NOMBRE": "LAGO GENERAL CARRERA EN DESAG\u00dcE", "ESTADO": "Vigente", "ESTE_84": 667488, "NORTE_84": 4809556, "COD_CUEN": "115", "COD_SUBC": "1151", "COD_SSUBC": "11517", "NOM_SSUBC": "Costeras Entre Rio Delta y Desague Lago Jose Miguel Carrera", "NOM_CUEN": "Rio Baker", "NOM_SUBC": "Vertiente N.  Lago J. Miguel Carrera (Exc.  R. Iba\u00a4ez)", "CINE_REG": "11", "COD_REG": 11, "NOM_REG": "Ays\u00e9n del General Carlos Ib\u00e1\u00f1ez del Campo", "CINE_PROV": "114", "COD_PROV": 114, "NOM_PROV": "General Carrera", "CINE_COM": "11401", "COD_COM": 11401, "NOM_COM": "Chile Chico", "LAT": -46.8464514499, "LONG": -72.8032034369, "FID_comuna": 19329, "CUT_REG": "11", "CUT_PROV": "114", "CUT_COM": "11401", "REGION_1": "Ays\u00e9n del General Carlos Ib\u00e1\u00f1ez del Campo", "PROVINCIA": "General Carrera", "COMUNA": "Chile Chico", "COD_CUEN_1": "115", "COD_SUBC_1": "1151", "COD_SSUB_1": "11517", "NOM_SSUB_1": "Costeras Entre Rio Delta y Desague Lago Jose Miguel Carrera", "Hectareas": 15003.4373332}}, {"type": "Feature", "geometry": {"type": "Point", "coordinates": [-72.86284575206408, -46.740541313921966]}, "properties": {"FID_Fluvio": 399, "REGION": "11", "COD_BNA": "11516002-8", "NOMBRE": "RIO LOS LEONES EN CARRETERA AUSTRAL", "ESTADO": "Vigente", "ESTE_84": 663261, "NORTE_84": 4821450, "COD_CUEN": "115", "COD_SUBC": "1151", "COD_SSUBC": "11516", "NOM_SSUBC": "Rio Delta", "NOM_CUEN": "Rio Baker", "NOM_SUBC": "Vertiente N.  Lago J. Miguel Carrera (Exc.  R. Iba\u00a4ez)", "CINE_REG": "11", "COD_REG": 11, "NOM_REG": "Ays\u00e9n del General Carlos Ib\u00e1\u00f1ez del Campo", "CINE_PROV": "114", "COD_PROV": 114, "NOM_PROV": "General Carrera", "CINE_COM": "11401", "COD_COM": 11401, "NOM_COM": "Chile Chico", "LAT": -46.7405413139, "LONG": -72.8628457521, "FID_comuna": 19310, "CUT_REG": "11", "CUT_PROV": "114", "CUT_COM": "11401", "REGION_1": "Ays\u00e9n del General Carlos Ib\u00e1\u00f1ez del Campo", "PROVINCIA": "General Carrera", "COMUNA": "Chile Chico", "COD_CUEN_1": "115", "COD_SUBC_1": "1151", "COD_SSUB_1": "11516", "NOM_SSUB_1": "Rio Delta", "Hectareas": 100126.130514}}, {"type": "Feature", "geometry": {"type": "Point", "coordinates": [-71.66979194064666, -46.58678134960684]}, "properties": {"FID_Fluvio": 396, "REGION": "11", "COD_BNA": "11520002-K", "NOMBRE": "RIO JEINIMENI EN CHILE CHICO", "ESTADO": "Vigente", "ESTE_84": 295472, "NORTE_84": 4837291, "COD_CUEN": "115", "COD_SUBC": "1152", "COD_SSUBC": "11521", "NOM_SSUBC": "Costeras entre Rio Jeinemeni y Rio San Jose", "NOM_CUEN": "Rio Baker", "NOM_SUBC": "Vertiente Sur Lago Jose Miguel Carrera", "CINE_REG": "11", "COD_REG": 11, "NOM_REG": "Ays\u00e9n del General Carlos Ib\u00e1\u00f1ez del Campo", "CINE_PROV": "114", "COD_PROV": 114, "NOM_PROV": "General Carrera", "CINE_COM": "11401", "COD_COM": 11401, "NOM_COM": "Chile Chico", "LAT": -46.5867813496, "LONG": -71.6697919406, "FID_comuna": 19303, "CUT_REG": "11", "CUT_PROV": "114", "CUT_COM": "11401", "REGION_1": "Ays\u00e9n del General Carlos Ib\u00e1\u00f1ez del Campo", "PROVINCIA": "General Carrera", "COMUNA": "Chile Chico", "COD_CUEN_1": "115", "COD_SUBC_1": "1152", "COD_SSUB_1": "11521", "NOM_SSUB_1": "Costeras entre Rio Jeinemeni y Rio San Jose", "Hectareas": 127131.796305}}, {"type": "Feature", "geometry": {"type": "Point", "coordinates": [-71.89344823756663, -46.55494181736843]}, "properties": {"FID_Fluvio": 397, "REGION": "11", "COD_BNA": "11521001-7", "NOMBRE": "RIO EL BAGNO EN CHILE CHICO", "ESTADO": "Vigente", "ESTE_84": 278209, "NORTE_84": 4840224, "COD_CUEN": "115", "COD_SUBC": "1152", "COD_SSUBC": "11521", "NOM_SSUBC": "Costeras entre Rio Jeinemeni y Rio San Jose", "NOM_CUEN": "Rio Baker", "NOM_SUBC": "Vertiente Sur Lago Jose Miguel Carrera", "CINE_REG": "11", "COD_REG": 11, "NOM_REG": "Ays\u00e9n del General Carlos Ib\u00e1\u00f1ez del Campo", "CINE_PROV": "114", "COD_PROV": 114, "NOM_PROV": "General Carrera", "CINE_COM": "11401", "COD_COM": 11401, "NOM_COM": "Chile Chico", "LAT": -46.5549418174, "LONG": -71.8934482376, "FID_comuna": 19303, "CUT_REG": "11", "CUT_PROV": "114", "CUT_COM": "11401", "REGION_1": "Ays\u00e9n del General Carlos Ib\u00e1\u00f1ez del Campo", "PROVINCIA": "General Carrera", "COMUNA": "Chile Chico", "COD_CUEN_1": "115", "COD_SUBC_1": "1152", "COD_SSUB_1": "11521", "NOM_SSUB_1": "Costeras entre Rio Jeinemeni y Rio San Jose", "Hectareas": 127131.796305}}, {"type": "Feature", "geometry": {"type": "Point", "coordinates": [-73.15045139078758, -46.50311218977853]}, "properties": {"FID_Fluvio": 398, "REGION": "11", "COD_BNA": "11420000-K", "NOMBRE": "RIO EXPLORADORES EN NACIMIENTO", "ESTADO": "Vigente", "ESTE_84": 641910, "NORTE_84": 4848389, "COD_CUEN": "114", "COD_SUBC": "1142", "COD_SSUBC": "11420", "NOM_SSUBC": "Rio Norte hasta Ventisquero Exploradores", "NOM_CUEN": "Costeras e Islas entre R Aisen y R Baker y Canal Gral. Martinez", "NOM_SUBC": "Rio Exploradores", "CINE_REG": "11", "COD_REG": 11, "NOM_REG": "Ays\u00e9n del General Carlos Ib\u00e1\u00f1ez del Campo", "CINE_PROV": "114", "COD_PROV": 114, "NOM_PROV": "General Carrera", "CINE_COM": "11401", "COD_COM": 11401, "NOM_COM": "Chile Chico", "LAT": -46.5031121898, "LONG": -73.1504513908, "FID_comuna": 19305, "CUT_REG": "11", "CUT_PROV": "114", "CUT_COM": "11401", "REGION_1": "Ays\u00e9n del General Carlos Ib\u00e1\u00f1ez del Campo", "PROVINCIA": "General Carrera", "COMUNA": "Chile Chico", "COD_CUEN_1": "114", "COD_SUBC_1": "1142", "COD_SSUB_1": "11420", "NOM_SSUB_1": "Rio Norte hasta Ventisquero Exploradores", "Hectareas": 2539.76663412}}]}