{"type": "FeatureCollection", "features": [{"type": "Feature", "geometry": {"type": "Point", "coordinates": [361480, 6666452]}, "properties": {"REGION": "4", "COD_BNA": "04313001-3", "NOMBRE": "RIO COCHIGUAZ EN EL PE\u00d1ON", "ESTADO": "Vigente", "ESTE_84": 361480, "NORTE_84": 6666452, "COD_CUEN": "043", "COD_SUBC": "0431", "COD_SSUBC": "04313", "NOM_SSUBC": "Rio Cochiguas Entre Bajo Quebrada Cha\u00a4ar y Rio Claro", "NOM_CUEN": "Rio Elqui", "NOM_SUBC": "Rio Claro", "CINE_REG": "04", "COD_REG": 4, "NOM_REG": "Coquimbo", "CINE_PROV": "041", "COD_PROV": 41, "NOM_PROV": "Elqui", "CINE_COM": "04105", "COD_COM": 4105, "NOM_COM": "Paiguano", "LAT": -30.1253518249, "LONG": -70.4379542636, "CUT_COM": "04105"}}, {"type": "Feature", "geometry": {"type": "Point", "coordinates": [355969, 6655437]}, "properties": {"REGION": "4", "COD_BNA": "04311001-2", "NOMBRE": "ESTERO DERECHO EN ALCOHUAZ", "ESTADO": "Vigente", "ESTE_84": 355969, "NORTE_84": 6655437, "COD_CUEN": "043", "COD_SUBC": "0431", "COD_SSUBC": "04310", "NOM_SSUBC": "Rio Derecho Hasta Quebrada Cogua", "NOM_CUEN": "Rio Elqui", "NOM_SUBC": "Rio Claro", "CINE_REG": "04", "COD_REG": 4, "NOM_REG": "Coquimbo", "CINE_PROV": "041", "COD_PROV": 41, "NOM_PROV": "Elqui", "CINE_COM": "04105", "COD_COM": 4105, "NOM_COM": "Paiguano", "LAT": -30.2240824385, "LONG": -70.4966482855, "CUT_COM": "04105"}}]}